README.md
setup.py
mara_config/__init__.py
mara_config/app_composing.py
mara_config/cli.py
mara_config/config.py
mara_config.egg-info/PKG-INFO
mara_config.egg-info/SOURCES.txt
mara_config.egg-info/dependency_links.txt
mara_config.egg-info/requires.txt
mara_config.egg-info/top_level.txt
mara_config/config_system/__init__.py
mara_config/config_system/config_display.py
mara_config/tests/__init__.py
mara_config/tests/test_config.py