Metadata-Version: 2.1
Name: mara-config
Version: 0.2.0
Summary: Mara app composing and configuration infrastructure.
Home-page: UNKNOWN
Author: Mara contributors
License: MIT
Platform: UNKNOWN
Provides-Extra: test
